miniomm/__init__.py
miniomm/config.py
miniomm/main.py
miniomm/miniomm.py
miniomm/namdbin.py
miniomm/namdxsc.py
miniomm/reporters.py
miniomm/unused.py
miniomm/util.py
miniomm-0.1.2.data/scripts/sbatch_many
miniomm-0.1.2.dist-info/METADATA
miniomm-0.1.2.dist-info/WHEEL
miniomm-0.1.2.dist-info/entry_points.txt
miniomm-0.1.2.dist-info/top_level.txt
miniomm-0.1.2.dist-info/RECORD
