Metadata-Version: 2.1
Name: miniomm
Version: 0.1.2
Summary: A simple OpenMM wrapper for common-case MD runs
Home-page: https://github.com/giorginolab/miniomm
Author: Toni Giorgino
Author-email: toni.giorgino@gmail.com
License: LGPL-3.0-or-later
Keywords: molecular dynamics
Platform: UNKNOWN
Classifier: Development Status :: 3 - Alpha
Classifier: Topic :: Scientific/Engineering :: Chemistry
Classifier: Topic :: Scientific/Engineering :: Bio-Informatics
Classifier: Topic :: Scientific/Engineering :: Physics
Classifier: License :: OSI Approved :: GNU Lesser General Public License v3 (LGPLv3)
